home_assistant_datasets/__init__.py
home_assistant_datasets/blueprint.py
home_assistant_datasets/hass_data.py
home_assistant_datasets/model_client.py
home_assistant_datasets/models.py
home_assistant_datasets/scrape.py
home_assistant_datasets/secrets.py
home_assistant_datasets/yaml_loaders.py
home_assistant_datasets/agent/__init__.py
home_assistant_datasets/agent/agent.py
home_assistant_datasets/agent/ai_task.py
home_assistant_datasets/agent/rate_limit.py
home_assistant_datasets/agent/retryable.py
home_assistant_datasets/agent/service_call.py
home_assistant_datasets/agent/timing.py
home_assistant_datasets/agent/trace_events.py
home_assistant_datasets/datasets/assist_data_loader.py
home_assistant_datasets/datasets/assist_eval_task.py
home_assistant_datasets/datasets/dataset_card.py
home_assistant_datasets/datasets/convert/__init__.py
home_assistant_datasets/datasets/convert/blueprint_schema.py
home_assistant_datasets/datasets/convert/intents.py
home_assistant_datasets/entity_state/__init__.py
home_assistant_datasets/entity_state/diff.py
home_assistant_datasets/metrics/__init__.py
home_assistant_datasets/metrics/accuracy.py
home_assistant_datasets/metrics/report.py
home_assistant_datasets/metrics/report_csv.py
home_assistant_datasets/metrics/report_suite.py
home_assistant_datasets/metrics/scrape_reader.py
home_assistant_datasets/metrics/token_stats.py
home_assistant_datasets/plugins/__init__.py
home_assistant_datasets/plugins/pytest_agent.py
home_assistant_datasets/plugins/pytest_data_loader.py
home_assistant_datasets/plugins/pytest_dataset.py
home_assistant_datasets/plugins/pytest_scrape.py
home_assistant_datasets/plugins/pytest_metrics/__init__.py
home_assistant_datasets/plugins/pytest_synthetic_home/__init__.py
home_assistant_datasets/tokenizer/chat_template.py
home_assistant_datasets/tokenizer/conversation.py
home_assistant_datasets/tokenizer/llama3/tokenizer_config.json
home_assistant_datasets/tool/__init__.py
home_assistant_datasets/tool/__main__.py
home_assistant_datasets-0.3.0.dist-info/METADATA
home_assistant_datasets-0.3.0.dist-info/WHEEL
home_assistant_datasets-0.3.0.dist-info/entry_points.txt
home_assistant_datasets-0.3.0.dist-info/top_level.txt
home_assistant_datasets-0.3.0.dist-info/RECORD
