Metadata-Version: 2.4
Name: home_assistant_datasets
Version: 0.3.0
Summary: Library and tools for building datasets related to Home Assistant.
Author-email: Allen Porter <allen.porter@gmail.com>
License-Expression: Apache-2.0
Project-URL: Source, https://github.com/allenporter/home_assistant_datasets
Project-URL: Repository, https://github.com/allenporter/home-assistant-datasets.git
Requires-Python: >=3.12
Requires-Dist: PyYAML>=6.0.1
Requires-Dist: mashumaro>=3.13
Requires-Dist: openai>=1.10.0
Requires-Dist: google-generativeai>=0.5.4
Requires-Dist: hass-client>=1.2.0
Requires-Dist: synthetic_home>=4.3.1
Requires-Dist: hass-client>=1.2.0
Requires-Dist: pyrate-limiter>=3.9.0
